setup.py
stats_calculations/Binomialdistribution.py
stats_calculations/Gaussiandistribution.py
stats_calculations/Generaldistribution.py
stats_calculations/__init__.py
stats_calculations.egg-info/PKG-INFO
stats_calculations.egg-info/SOURCES.txt
stats_calculations.egg-info/dependency_links.txt
stats_calculations.egg-info/not-zip-safe
stats_calculations.egg-info/top_level.txt