Metadata-Version: 1.0
Name: stats-calculations
Version: 0.1
Summary: Gaussian distributions
Home-page: UNKNOWN
Author: M Abhishek
Author-email: abhishek.nithya@gmail.com
License: UNKNOWN
Platform: UNKNOWN
